MANIFEST.in
requirements.txt
setup.py
src/zato/__init__.py
src/zato/common/__init__.py
src/zato/common/api.py
src/zato/common/audit.py
src/zato/common/audit_log.py
src/zato/common/broker_message.py
src/zato/common/ccsid_.py
src/zato/common/component_info.py
src/zato/common/const.py
src/zato/common/defaults.py
src/zato/common/dispatch.py
src/zato/common/exception.py
src/zato/common/haproxy.py
src/zato/common/hl7.py
src/zato/common/http_.py
src/zato/common/ibm_mq.py
src/zato/common/in_ram.py
src/zato/common/ipaddress_.py
src/zato/common/json_.py
src/zato/common/json_internal.py
src/zato/common/json_rpc.py
src/zato/common/json_schema.py
src/zato/common/kv_data.py
src/zato/common/log_message.py
src/zato/common/match.py
src/zato/common/microopt.py
src/zato/common/mssql_direct.py
src/zato/common/nav.py
src/zato/common/pubsub.py
src/zato/common/repo.py
src/zato/common/scheduler.py
src/zato/common/settings_db.py
src/zato/common/sftp.py
src/zato/common/simpleio_.py
src/zato/common/typing_.py
src/zato/common/user.py
src/zato/common/vault_.py
src/zato/common/version.py
src/zato/common/wsx_client.py
src/zato/common/xml_.py
src/zato/common/crypto/__init__.py
src/zato/common/crypto/api.py
src/zato/common/crypto/const.py
src/zato/common/crypto/hash_.py
src/zato/common/crypto/secret_key.py
src/zato/common/crypto/totp_.py
src/zato/common/events/__init__.py
src/zato/common/events/client.py
src/zato/common/events/common.py
src/zato/common/ext/__init__.py
src/zato/common/ext/_dataclasses.py
src/zato/common/ext/configobj_.py
src/zato/common/ext/dataclasses.py
src/zato/common/ext/typing_extensions.py
src/zato/common/ext/validate_.py
src/zato/common/ext/imbox/__init__.py
src/zato/common/ext/imbox/imap.py
src/zato/common/ext/imbox/imbox.py
src/zato/common/ext/imbox/messages.py
src/zato/common/ext/imbox/parser.py
src/zato/common/ext/imbox/query.py
src/zato/common/ext/imbox/utils.py
src/zato/common/ext/imbox/version.py
src/zato/common/ext/imbox/vendors/__init__.py
src/zato_common_holocene.egg-info/PKG-INFO
src/zato_common_holocene.egg-info/SOURCES.txt
src/zato_common_holocene.egg-info/dependency_links.txt
src/zato_common_holocene.egg-info/namespace_packages.txt
src/zato_common_holocene.egg-info/not-zip-safe
src/zato_common_holocene.egg-info/requires.txt
src/zato_common_holocene.egg-info/top_level.txt