Metadata-Version: 2.1
Name: zato-common-holocene
Version: 3.2.1
Summary: Constants and utils common across the whole of Zato ESB and app server (https://zato.io)
Home-page: https://zato.io
Author: Zato Source s.r.o.
Author-email: info@zato.io
License: GNU Lesser General Public License v3 (LGPLv3)
Keywords: soa eai esb middleware messaging queueing asynchronous integration performance http zeromq framework events agile broker messaging server jms enterprise python middleware clustering amqp nosql websphere mq wmq mqseries ibm amqp zmq
Platform: OS Independent
Classifier: Development Status :: 5 - Production/Stable
Classifier: Environment :: Console
Classifier: Framework :: Buildout
Classifier: Intended Audience :: Customer Service
Classifier: Intended Audience :: Developers
Classifier: Intended Audience :: Financial and Insurance Industry
Classifier: Intended Audience :: Healthcare Industry
Classifier: Intended Audience :: Information Technology
Classifier: Intended Audience :: Telecommunications Industry
Classifier: License :: OSI Approved :: GNU Lesser General Public License v3 (LGPLv3)
Classifier: Natural Language :: English
Classifier: Operating System :: OS Independent
Classifier: Programming Language :: C
Classifier: Programming Language :: Python :: 2 :: Only
Classifier: Programming Language :: Python :: 2.7
Classifier: Topic :: Database
Classifier: Operating System :: POSIX :: Linux
Classifier: Operating System :: MacOS :: MacOS X
Classifier: Topic :: Internet
Classifier: Topic :: Internet :: WWW/HTTP :: WSGI :: Server
Classifier: Topic :: Internet :: File Transfer Protocol (FTP)
Classifier: Topic :: Software Development :: Libraries :: Python Modules
Classifier: Topic :: Software Development :: Object Brokering
